async_bowl/__init__.py
async_bowl/adapter.py
async_bowl/cache.py
async_bowl/element_getter.py
async_bowl/exceptions.py
async_bowl/item.py
async_bowl/item_clean.py
async_bowl/models.py
async_bowl/task_pool.py
async_bowl/utils.py
async_bowl/wrapper_rabbitmq.py
async_bowl/wrapper_redis.py
async_bowl-0.1.0.dist-info/DESCRIPTION.rst
async_bowl-0.1.0.dist-info/METADATA
async_bowl-0.1.0.dist-info/RECORD
async_bowl-0.1.0.dist-info/WHEEL
async_bowl-0.1.0.dist-info/metadata.json
async_bowl-0.1.0.dist-info/top_level.txt
